{"type":"scene","pointers":["-71,52","-71,53","-71,54","-71,55","-71,56","-71,57","-71,58","-71,59","-71,60","-71,61","-71,62","-71,63","-71,64","-71,65","-71,66","-71,67","-71,68","-71,69","-71,70","-71,71","-70,52","-70,53","-70,54","-70,55","-70,56","-70,57","-70,58","-70,59","-70,60","-70,61","-70,62","-70,63","-70,64","-70,65","-70,66","-70,67","-70,68","-70,69","-70,70","-70,71","-69,52","-69,53","-69,54","-69,55","-69,56","-69,57","-69,58","-69,59","-69,60","-69,61","-69,62","-69,63","-69,64","-69,65","-69,66","-69,67","-69,68","-69,69","-69,70","-69,71","-68,52","-68,53","-68,54","-68,55","-68,56","-68,57","-68,58","-68,59","-68,60","-68,61","-68,62","-68,63","-68,64","-68,65","-68,66","-68,67","-68,68","-68,69","-68,70","-68,71","-67,52","-67,53","-67,54","-67,55","-67,56","-67,57","-67,58","-67,59","-67,60","-67,61","-67,62","-67,63","-67,64","-67,65","-67,66","-67,67","-67,68","-67,69","-67,70","-67,71","-66,52","-66,53","-66,54","-66,55","-66,56","-66,57","-66,58","-66,59","-66,60","-66,61","-66,62","-66,63","-66,64","-66,65","-66,66","-66,67","-66,68","-66,69","-66,70","-66,71","-65,52","-65,53","-65,54","-65,55","-65,56","-65,57","-65,58","-65,59","-65,60","-65,61","-65,62","-65,63","-65,64","-65,65","-65,66","-65,67","-65,68","-65,69","-65,70","-65,71","-64,52","-64,53","-64,54","-64,55","-64,56","-64,57","-64,58","-64,59","-64,60","-64,61","-64,62","-64,63","-64,64","-64,65","-64,66","-64,67","-64,68","-64,69","-64,70","-64,71","-63,52","-63,53","-63,54","-63,55","-63,56","-63,57","-63,58","-63,59","-63,60","-63,61","-63,62","-63,63","-63,64","-63,65","-63,66","-63,67","-63,68","-63,69","-63,70","-63,71","-62,52","-62,53","-62,54","-62,55","-62,56","-62,57","-62,58","-62,59","-62,60","-62,61","-62,62","-62,63","-62,64","-62,65","-62,66","-62,67","-62,68","-62,69","-62,70","-62,71","-61,52","-61,53","-61,54","-61,55","-61,56","-61,57","-61,58","-61,59","-61,60","-61,61","-61,62","-61,63","-61,64","-61,65","-61,66","-61,67","-61,68","-61,69","-61,70","-61,71","-60,52","-60,53","-60,54","-60,55","-60,56","-60,57","-60,58","-60,59","-60,60","-60,61","-60,62","-60,63","-60,64","-60,65","-60,66","-60,67","-60,68","-60,69","-60,70","-60,71","-59,52","-59,53","-59,54","-59,55","-59,56","-59,57","-59,58","-59,59","-59,60","-59,61","-59,62","-59,63","-59,64","-59,65","-59,66","-59,67","-59,68","-59,69","-59,70","-59,71","-58,52","-58,53","-58,54","-58,55","-58,56","-58,57","-58,58","-58,59","-58,60","-58,61","-58,62","-58,63","-58,64","-58,65","-58,66","-58,67","-58,68","-58,69","-58,70","-58,71","-57,52","-57,53","-57,54","-57,55","-57,56","-57,57","-57,58","-57,59","-57,60","-57,61","-57,62","-57,63","-57,64","-57,65","-57,66","-57,67","-57,68","-57,69","-57,70","-57,71","-56,52","-56,53","-56,54","-56,55","-56,56","-56,57","-56,58","-56,59","-56,60","-56,61","-56,62","-56,63","-56,64","-56,65","-56,66","-56,67","-56,68","-56,69","-56,70","-56,71","-55,52","-55,53","-55,54","-55,55","-55,56","-55,57","-55,58","-55,59","-55,60","-55,61","-55,62","-55,63","-55,64","-55,65","-55,66","-55,67","-55,68","-55,69","-55,70","-55,71","-54,52","-54,53","-54,54","-54,55","-54,56","-54,57","-54,58","-54,59","-54,60","-54,61","-54,62","-54,63","-54,64","-54,65","-54,66","-54,67","-54,68","-54,69","-54,70","-54,71","-53,52","-53,53","-53,54","-53,55","-53,56","-53,57","-53,58","-53,59","-53,60","-53,61","-53,62","-53,63","-53,64","-53,65","-53,66","-53,67","-53,68","-53,69","-53,70","-53,71","-52,52","-52,53","-52,54","-52,55","-52,56","-52,57","-52,58","-52,59","-52,60","-52,61","-52,62","-52,63","-52,64","-52,65","-52,66","-52,67","-52,68","-52,69","-52,70","-52,71"],"timestamp":1584129288057,"content":[{"file":"bin/game.js","hash":"QmX6L8hKhaMvKL3nDQHgrtvUxRuJj86GxpxFf1p1nJKQML"},{"file":"images/UI_TX.png","hash":"QmPMPSgh3CQmzEHbux12G8dy5YR5BzShb9f5gYzCvuJ6tV"},{"file":"images/balanceBack.png","hash":"QmYUskhUnqzaJceAFZpxG1JXSPZBhN2cR51q75KW4UEfVy"},{"file":"images/balanceBottom.png","hash":"QmbT23MPiByU8yDpyqYAuP3Y1jyCjDnUP6PcRTS3KgQLaA"},{"file":"images/balanceButton.png","hash":"QmY7DXGhmmhFYwP4pcB41CRYv8DovTx45wfTZ4mxgjS6p6"},{"file":"images/balanceButtonClear.png","hash":"QmZjYJ1XUqutVGL6CM3GCcuspAeNTTtbiDcEQ3P2sRkQAP"},{"file":"images/blackButton.png","hash":"QmNWHvGN6gDKi1mG3HxEw3HtNaqjepQNcFJN7UCKbMfBhh"},{"file":"images/btnauth.png","hash":"QmcFgHRvw2Hw3haBfJxyhz9Au7sbE9XsQdsaXoRZRfUEQe"},{"file":"images/btnexchange.png","hash":"QmTAF11hCiU1cRsQ38kekftLp6TCpCLsnGTUuF6jodaUk6"},{"file":"images/btnswap.png","hash":"QmU42q5zHLPoCXt27M58EWgkkzxKdTv1dxEZevWwaNqofz"},{"file":"images/btnverify.png","hash":"QmbQvuTqPgb8E225jT36tDurnyukqo3sbVPuwgLCV8iSnG"},{"file":"images/close-icon3.png","hash":"QmWGgpYLTnTmE6J26Wp6P4DdwxhmwyCxeSyEv9n5EqMPLZ"},{"file":"images/dg.png","hash":"QmWP2uvx127agY4ScoUxq5akieX1cAUCFTijkPu2P5Cdjv"},{"file":"images/dj-TX.png","hash":"QmRqDkdtqbCD3g71HX73aw731coWRPwxKdCtXuNVYhyJH6"},{"file":"images/eth.png","hash":"QmdZ53kHfFWtU1PN81Yrm6adPGC9CsBXZHW5pRqfBKuGU8"},{"file":"images/ethinput.png","hash":"QmR8Q52Jfu7TM1FcKttyHK2cr1wUNVH6Lxn2Gqva9ZRLLU"},{"file":"images/exmark.png","hash":"QmPnR4wStLCSj2UXZAys6s1wRAv1McH8R4NryoBqBMQptN"},{"file":"images/grayButton.png","hash":"QmfNWyRNCLmy3ESUzGSTCcuqXLXdevc2qXxzrzr7vX5yBQ"},{"file":"images/logoDG.png","hash":"QmbVQLQTqG46TByQGupSeCRhWp4roA9CC2MKdDTtNtX3b8"},{"file":"images/mana.png","hash":"QmPiShMp7pChr8FnWzsBbbmpZn77s1vSnNfzSfQ3ZG5hiA"},{"file":"images/manainput.png","hash":"QmVcbRXDjNuuKiXvTbqBHLVhhmMHVpKQL4ztWxinEoEEBV"},{"file":"images/mark.png","hash":"QmQ8hVG2rAhTs15CjBwS9brEVgXDAavdmYx9JGfJDwx4wt"},{"file":"images/music.png","hash":"QmQBA5D7x14QkUfGkC7Ym1sYsDQmXbsDSv5Jc79uAFzyDo"},{"file":"images/notificationBack.png","hash":"QmYD2Dv6nn1KynmmrAYG7HrWiHLMNQikrf1MGGQB4PsQDG"},{"file":"images/notificationButton.png","hash":"QmXgSuiUoSHz8Pekpuc41THFk1kkmjdjT4Xvu36vuzDfrt"},{"file":"images/progress-logo.png","hash":"Qmc3ArxoXMDwMMoux6Zo6ioiKU6APHSWRsJHTfJXfKVSou"},{"file":"images/redButton.png","hash":"QmXJbEBb4X4ihNE4rfJUcZjq5K1nwFkQ4mmmcyzNgxrif5"},{"file":"images/refresh.png","hash":"QmNPitoS161Z89kzUy3WT39cUhcmB2QkDeYhmcSMa6Eddu"},{"file":"images/swap.png","hash":"QmeqnkfdTicKq7ndLFuTPC9GYyno9q4Q9iFdhRPfb2JXsK"},{"file":"images/winningNumbersBack.png","hash":"QmbHHTNyEK7bNeBnncM3wz26zjF4sRRPMZrW9YpheBim5W"},{"file":"materials/alpha.png","hash":"QmW819vBbErz5sa9mWhQ9vgsuui5gvG6H51NpLNuyYV4kB"},{"file":"models/AstonMartin_01.glb","hash":"Qmep9z5AdRGLfzKvJEX1HKQnUS5brPekStfjXoZDYFm13G"},{"file":"models/AstonMartin_02.glb","hash":"QmWPKwPBvLn33FLseSV3VLe9xaB4MEmxgV42cobcScrd2W"},{"file":"models/Booth_01.glb","hash":"QmZDzs8WcoRDRDgUwdFT23VhjTXQhQqfDSsVPDZQxFynxr"},{"file":"models/Booth_02.glb","hash":"QmWspJWwAhCUKDGxDtCiHh5YG4SZua931TznvJZR6WqCZa"},{"file":"models/Booth_03.glb","hash":"QmUAe1Zk4J8szjQoL3Kh9HAxYhdmqUn8sEeqwCCpozPQGf"},{"file":"models/Booth_04.glb","hash":"QmaykWJNC7VbpQPkGeMwpTqbfNi4VqTNH4ttumMoM8HcCH"},{"file":"models/Booth_05.glb","hash":"QmSK8vq8NoqPXXLkzRNAhpycYHAQ6GAdQnQygeh9YmgCDX"},{"file":"models/Booth_06.glb","hash":"QmQ112LSvQsfq12zmPJBXFyq4kURcv2U6YpzWRzzxCKjNA"},{"file":"models/Booth_07.glb","hash":"QmcGoxMWrEmusUmiXSB2ePPecY8w1emGXvJaPu7g2NWXue"},{"file":"models/Booth_08.glb","hash":"QmewSqAPXmLAe41VzRoJhaFcH75pawyJu8b2TX9aXs8kw6"},{"file":"models/DJ-Set/ButtonA.glb","hash":"QmPixBWZYNJ6Tbd3mHjBRoMHomQ2mj5eR38DPemABtTPDy"},{"file":"models/DJ-Set/ButtonB.glb","hash":"QmShApHN8CidZvMucsQrRUwSSeQ4EkNr7BJgPs92JiNdH4"},{"file":"models/DJ-Set/ButtonC.glb","hash":"QmeMzNStvv9n2WidFAiYefs4BXjbSJUZYJp9r5nPQVLmxH"},{"file":"models/DJ-Set/ButtonD.glb","hash":"QmfKT8rg3ZW19RFuadE8XbzkTxQRmyory93FyXd3iwp1jv"},{"file":"models/DJ-Set/ButtonE.glb","hash":"QmW4Yipjo4PvahnUG2RrU12y3zZsCVzBRxyiQ7fvcR6beX"},{"file":"models/DJ-Set/ButtonF.glb","hash":"QmWrribjaqdnYgT54NVa91QepuHunwHjk8dE2sf4ji9Fnm"},{"file":"models/DJ-Set/ButtonG.glb","hash":"QmSVQSqJrJVYUXyM5uvztsh63W3S3e2VCMY3j9L3KdnTtz"},{"file":"models/DJ-Set/ButtonH.glb","hash":"QmdaYqwk3GLkWKb5u6smHhpzesqE1ZRP44o78McpSseQkd"},{"file":"models/DJ-Set/ButtonI.glb","hash":"QmUa1knzAf4TxWJZPZ3a4e4jDhTGp1b18a2tAywJVxa17V"},{"file":"models/DJ-Set/DJ-Set.glb","hash":"QmWf1RkYKSdXvXowFbhtrsctGm2vrBxkWGCZfgidjtKFiS"},{"file":"models/DJ-Set/Disc_A.glb","hash":"QmW2ecA4Um9Rmgc3C7zQuupnZzxRW3y7bgJn9fLLAENeit"},{"file":"models/DJ-Set/Disc_B.glb","hash":"QmUgkgHguGRzGAUCMh4jUWjsrRv668zpEBcjTrjAMX58xn"},{"file":"models/DJ-Set/Fire_Button.glb","hash":"QmQjSnYWew3tPVaj816oBZ5xBQyjKEue8CYFffcRVDRV48"},{"file":"models/DJ-Set/Play_Me.glb","hash":"QmWsqFAkF3ZGKEXzNNsg8L8nPQqMeyFu1vt94vNQUxVdPN"},{"file":"models/Elevator.glb","hash":"QmdWRgZWgNPKvcmYt9sFUCyQhcntaHgkL2STXvReRZEVe8"},{"file":"models/FireConcertStage.glb","hash":"QmRYHNAjvkfe2B8HLiVp2KHqmjvbxh2oAdCHbjLukLA85L"},{"file":"models/FortuneCat.glb","hash":"QmfRBkhHiNmuFhGrzir3vJwFySTJh9bQ5dB2K8AsHbHebW"},{"file":"models/Lambo_01.glb","hash":"QmQLV8jCd9uPxQ6AXLhT2MDn4RbdubaScRjjhy87z1a3jL"},{"file":"models/Lift.glb","hash":"Qmdq2SYLo6nvVQZJ9Bo2cvdCLr2iDAVaQXPSWpYgoEN5NN"},{"file":"models/LightsDownConcertStage.glb","hash":"QmRBa47d4Y52oN78peMZQt79GpZ8AkKvkV8L1c2hyswgaY"},{"file":"models/LightsUpConcertStage.glb","hash":"QmRVgCYChwHgJ4YEZbxnrNZxyHminmGbynY2xUPZQzcoCj"},{"file":"models/Lights_Center.glb","hash":"Qmc8bw6cZHqPzfvYZaG5fUBXvvMETgpW5u4Bc21FGkzTpV"},{"file":"models/Lights_Wheel_01.glb","hash":"QmSbHmpLyK5dFF1LHzf1AsdN1gfi9HRJWcB6QbfyGUnUNN"},{"file":"models/Lights_Wheel_02.glb","hash":"QmPQdAFYUMYp1iDDdppg59KxUokaTbzBQMzr6ZANcKkxyk"},{"file":"models/Message.glb","hash":"QmPGjRc8Q7VbNmWn8qYjxcNZwvhtAgXyqfpi3wCYLED4gN"},{"file":"models/PoliceCar_01.glb","hash":"QmU3Ekv84tBaW2RXkCxDZXiPs2CRUao7Dy1ex7jnGXuPss"},{"file":"models/Pyrotechnics.glb","hash":"QmTG9EV299sskh6YR86KjgDLgQtkKc18hkoS5Qfd4wPhg7"},{"file":"models/Ship.glb","hash":"QmbZNKM8qkd9gwXsaBrAdbXEYys6Yd3ZWQTFsTSE8PwqfS"},{"file":"models/SportCar_01.glb","hash":"QmRRkkeqRvfTjPgQFNCNFmg8G6ya2vwac438rcC3Gb5ED3"},{"file":"models/SpotLightBackConcert.glb","hash":"QmVMaSTRyDAG3k5S6ThF6XDfZbUmT4KFRZ7xJw1eM1siWh"},{"file":"models/SpotLightCat.glb","hash":"QmNgxar2GKoiZVgML8pR5ETDPAS6htWWPiUqiEpLsn2uHv"},{"file":"models/VegasPlaza.glb","hash":"QmdhfvkNc1NeEXrZXWCWVpQPwB7Vq7aaMPrZDSAhiSBYSx"},{"file":"models/Wheel.glb","hash":"QmRypce8DWkSmKEoPBRThksyV9DUF4yeZLB7xVq39KJxmD"},{"file":"models/roulette/chips/chip_0_05eth.bin","hash":"Qmb8tDF2Y6kwHMvadVP3pJMd7LShKcKzoFzTq8FfHwzYks"},{"file":"models/roulette/chips/chip_0_05eth.gltf","hash":"QmcG4uYd69ayYW1ybwCjkreGkBDsh96d9TsFLQhzyinw6U"},{"file":"models/roulette/chips/chip_0_1eth.bin","hash":"QmZw3Lx2VZ3XTM8LzLKZrAspvu9Jyn2hJUaGn8s4Luzj3d"},{"file":"models/roulette/chips/chip_0_1eth.gltf","hash":"QmWyjDW61gTvmTYMoKj3JfyT5ppJ3LKXrKRQ99uVNn8rPd"},{"file":"models/roulette/chips/chip_0_5eth.bin","hash":"QmZgVVEc6FUQxY6k4pMc47E82TyUtWWGsmJSYKux4BBCyK"},{"file":"models/roulette/chips/chip_0_5eth.gltf","hash":"QmcFh8dnzewmzXBNJVfPQjxZ81m8UH17eQA5XR62EKBsFt"},{"file":"models/roulette/chips/chip_1eth.bin","hash":"QmRv4zS4rAkmkak5kdpdCpNHcAoafYgDs4xFUq9eksfRy4"},{"file":"models/roulette/chips/chip_1eth.gltf","hash":"QmcMvTXyospctY5nPNsyWFYi9mV9jDNSn9GooQjfcjjvF8"},{"file":"models/roulette/chips/chips.jpg","hash":"Qmf6YTFoEFbhDudspRgYZxtvyvFeRXEcQKNK5fAyg1meCM"},{"file":"models/roulette/roulette_ball.glb","hash":"QmNzdCySsPHZmsLWcKKm958FUT4QURHJttKqHPesGLiuaa"},{"file":"models/roulette/roulette_table.glb","hash":"QmX7pegqndFvDLcB2USsLzyLDWzfpFi9tCbz5xBnTSgERe"},{"file":"models/roulette/roulette_table_v2.glb","hash":"QmZp2tMmEAbRfU86cYhQCA5A2bMFb1GfVdQfPKk7vL7YQu"},{"file":"models/roulette/roulette_wheel.glb","hash":"QmPGp9yGah8ugwzvuvu3DhRSzX8eYzXs1nYvA5Nzfr98cE"},{"file":"models/roulette/roulette_wheel_numbers.glb","hash":"QmX1RL7GNW7BNzuTWrce6We7npbCsgTSxKVwKfVWzaYtMk"},{"file":"models/roulette/table_v1/Image_0.png","hash":"QmPtCTmoJm1dbSZyKD9N8j1WtkzuEEJPfcPLoGa4yEyyQ9"},{"file":"models/roulette/table_v1/Image_1.png","hash":"QmRiSpzMA38CMgF4kqeqREkTUy8YqytXux54MiUzUHCJ6i"},{"file":"models/roulette/table_v1/Image_2.png","hash":"QmcFgb33XWkx31U3CM1N5WQf758CkM3V1MC4MquyhCJUt8"},{"file":"models/roulette/table_v1/Image_3.png","hash":"QmPP465ZbXs2W4xW88V5eY9ZKc4qdyfez814ubuGaqvxiA"},{"file":"models/roulette/table_v1/Image_4.png","hash":"QmTYPntxRi1Bfysr6HrgP4JQsBcf5FtGAE9spgrKvWg2T6"},{"file":"models/roulette/table_v1/roulette_table_v1_numbers.bin","hash":"QmPxfuWA2e5gcc3QEYL2qdtK3sh5NDVS1KhpciUxSceLk2"},{"file":"models/roulette/table_v1/roulette_table_v1_numbers.gltf","hash":"QmPEtjQp6sC3QKMeC2rywZLmRxftLbbg5medrJfrLJTirC"},{"file":"models/roulette/table_v1/roulette_table_v1_table.bin","hash":"QmW2e1tfxViTUNd5Ha19Kq5gVaEkkhiUCRDRp9iRK3cb8F"},{"file":"models/roulette/table_v1/roulette_table_v1_table.gltf","hash":"QmcGj4stCiSkciWyhghvwiUbjn7ohN6R9nY8WQqTt6rZe1"},{"file":"models/roulette/ui/coins_glow.glb","hash":"QmVdFL1yEAp6MwBAK2FZp2qNmjcYmeoYpKB8HyieAQK4qj"},{"file":"models/roulette/ui/digit_glow.glb","hash":"QmNhsgFGt6qzb9ubNy8jkJg1SReAoPArCAxcwqQ88hcQPh"},{"file":"models/roulette/ui/table_glow.glb","hash":"QmRSxxSCQbT9eR1k2FkiYJNBxfsEBuY8SAyowDbPzJ5Q9q"},{"file":"models/roulette/ui/table_glow_v2.glb","hash":"QmcgbEMuVwA6h1HuEJS5SKc36DpiNjrHcR9gS8zGzQVyJm"},{"file":"models/roulette/ui/wheel_glow.glb","hash":"QmNcrwdaSBwGEGcfyhbp4F1EPJdMdAo2CnScspPrX4XrXo"},{"file":"models/slots/slotMachineArm.bin","hash":"QmNf2kHybRrFfD35dKenrM5YS8AL1Hjhxza2BQgyK6GERm"},{"file":"models/slots/slotMachineArm.gltf","hash":"QmU6b66hRk4copKrpwmU4n8eATWXDGUbih98HpSx4fTRPr"},{"file":"models/slots/slotMachineButton.bin","hash":"QmWxxakdfwxcqmFNvF7X3NRHbdVLeno8qK1AQw7ctCvWpU"},{"file":"models/slots/slotMachineButton.gltf","hash":"QmdBm3mSGMkVcvjENy1Mg5QKgdRWooWj2VFBCaYEL5t7Zm"},{"file":"models/slots/slotMachineWheel_11.bin","hash":"QmboegZJDHHzocsrsbW4HSfMmPoopWHaUUCmceif6if9VN"},{"file":"models/slots/slotMachineWheel_11.gltf","hash":"QmQ1tQa5MVfyvUUwpnVmDxbBMqvn9hmBosGAT7veBfk61f"},{"file":"models/slots/slotMachineWheel_25.bin","hash":"QmboegZJDHHzocsrsbW4HSfMmPoopWHaUUCmceif6if9VN"},{"file":"models/slots/slotMachineWheel_25.gltf","hash":"QmXD6LQAukptqDPjMQVXFJ7aAQpuuf5kd23hFmgb3f6vZm"},{"file":"models/slots/slotMachineWheel_3.bin","hash":"QmboegZJDHHzocsrsbW4HSfMmPoopWHaUUCmceif6if9VN"},{"file":"models/slots/slotMachineWheel_3.gltf","hash":"QmZe2MwAJRcyaSzVpHmvFo42ZoGMih7YBubwqsvN6vGJxi"},{"file":"models/slots/slotMachineWheel_4.bin","hash":"QmboegZJDHHzocsrsbW4HSfMmPoopWHaUUCmceif6if9VN"},{"file":"models/slots/slotMachineWheel_4.gltf","hash":"QmdLdW6EaDtLhZtKTi9YLRGGemav6Cd2DdxNQYcSNWsDzm"},{"file":"models/slots/slotMachineWheel_9.bin","hash":"QmboegZJDHHzocsrsbW4HSfMmPoopWHaUUCmceif6if9VN"},{"file":"models/slots/slotMachineWheel_9.gltf","hash":"QmcFbYjgweaPHYL2cPsGiL13ixseynGxN4GhBLPYUHihUN"},{"file":"models/slots/slotMachine_11_collider.bin","hash":"Qmchne5GucCVbnBMbmo5rpvzbocWrz7yw2zrx6hcUCqTHn"},{"file":"models/slots/slotMachine_11_collider.gltf","hash":"QmTrBebw1yHVUi42Mt9cGwftACQG4DXdmq8cX2oPLpAJET"},{"file":"models/slots/slotMachine_25_collider.bin","hash":"Qmchne5GucCVbnBMbmo5rpvzbocWrz7yw2zrx6hcUCqTHn"},{"file":"models/slots/slotMachine_25_collider.gltf","hash":"QmeTkS7UGsW8hTXsVmojMJdLhYPCjSoQ6yk2QdT1jrsXWk"},{"file":"models/slots/slotMachine_3_collider.bin","hash":"Qmchne5GucCVbnBMbmo5rpvzbocWrz7yw2zrx6hcUCqTHn"},{"file":"models/slots/slotMachine_3_collider.gltf","hash":"Qmb9m39MmcfnUX4XoBZayaxCv7Ds1Mhkq8S8zvN31MpGQE"},{"file":"models/slots/slotMachine_4_collider.bin","hash":"Qmchne5GucCVbnBMbmo5rpvzbocWrz7yw2zrx6hcUCqTHn"},{"file":"models/slots/slotMachine_4_collider.gltf","hash":"QmdkAriBc1i8aCfQEoZfiz5YCfWJsA6mh1rHhfw1Mf8noN"},{"file":"models/slots/slotMachine_9_collider.bin","hash":"Qmchne5GucCVbnBMbmo5rpvzbocWrz7yw2zrx6hcUCqTHn"},{"file":"models/slots/slotMachine_9_collider.gltf","hash":"Qmam2pTEQjPTPzWTLCuJyeHk8dVNbAX2NMLo2aigBnumBt"},{"file":"models/slots/slot_machine_tower.glb","hash":"QmQhkjhvtgoRxATkm9Z79JxyLDdmNQ1dkSKEWFZMF5Ur7T"},{"file":"models/slots/texture11.png","hash":"QmT8XzmLngu4Rwvg2xTkkPYrQfnakekUJYdyQJMjnDzJiK"},{"file":"models/slots/texture25.png","hash":"QmdUJL9py1TvhyWgeeWqZrhVXvXaJgMvtvStBjEQFzWrq4"},{"file":"models/slots/texture3.png","hash":"QmPVRxQCpsg9HjTWbcG1yhef1bwA4JnG1jHsqFJZT3SGMX"},{"file":"models/slots/texture4.png","hash":"QmUeibK4mjTSq95tXrRja5XZmeGY9frhK1nBRqTqLKgTFh"},{"file":"models/slots/texture9.png","hash":"QmXwdvFNnxUL2YMikoPKyxBBdaUSVSWrjg6Q5tnd5QBZoz"},{"file":"scene.json","hash":"Qmcp4cfivh3QozG5p4UCWPWxiFKvRzYh6HtSSob9hFxboZ"},{"file":"sounds/Get_Ready.mp3","hash":"QmaY7wqLkpHZyDRQCRbaoRLAGBMMPgX7iNMQyyrauP6xPs"},{"file":"sounds/Run.mp3","hash":"QmaCFDjTTQtzTBeEprBLHMQitC1NQFNHveKgMM8oknmNQ5"},{"file":"sounds/Skyline.mp3","hash":"QmR1WZrA1oQKL58wWuv4uxvwq5MmoE7ULnBC6ckCkEfrfz"},{"file":"sounds/bass-drop.mp3","hash":"QmNxdBVHhE91HqMZtgACzJp74rsUXfa2YxWcs6yauJRr7R"},{"file":"sounds/bitconnect-sound.mp3","hash":"QmbLJyK2HJjiVZKvK7xaHXkTos5NjdbpNGzWxqaWKZ8Pnn"},{"file":"sounds/clap.mp3","hash":"QmUKTwo1sXqDx6hM7PmAgLpecje4ydH47dXsJjukkFZWXY"},{"file":"sounds/dj-scratch.mp3","hash":"QmRwTSmh4upNSUqx971phdZQo8MYowHX7ebYwWwqmqWK48"},{"file":"sounds/dj-scratch_02.mp3","hash":"QmNPgF5HznDkjhALW1AJNyBenJ876oTVkgQsTroUxbW7nS"},{"file":"sounds/dj-scratch_03.mp3","hash":"QmZiHHXFko9dzzxbi45ksK7MbYcn2CNULBosWecXUKfi2v"},{"file":"sounds/dj-scratch_04.mp3","hash":"QmPypViJnvmYDckYLHuDD6LLtBV7Tz13XZFhqcYLkG1oMj"},{"file":"sounds/electric-sound.mp3","hash":"QmPAEDR3fZ8twGQaJzUJFpSrfw1tD7TZhxcVFo4jCW6qfg"},{"file":"sounds/fire-sound.mp3","hash":"QmXAqKAg2LHq5VQBQGTjK4CQjwgUP9xqduvmwTf2nve2EU"},{"file":"sounds/horn.mp3","hash":"QmVagLyHd2Y5LXrw768pqAxrUEG9yp7gHoJn2h1Es9s8yY"},{"file":"sounds/kick.mp3","hash":"QmUHAJF5TppoCSYYz411ir3d7ts3q3rCHqU5S6xwbrqfky"},{"file":"sounds/laser.mp3","hash":"QmTRgLoqYcEYSYTMgfQvEZstzW544L1PZmcbMbSi3wwvX3"},{"file":"sounds/oh-yeah.mp3","hash":"QmRistJLDtWGwZ57aZsrfAv2C5hR9eiU38XJcU2ZcRb4VU"},{"file":"sounds/orchestra-hit.mp3","hash":"Qmd9LQGcxwyA5GiBYmh7rifRR32EUr4QiewTDEW3DSALDR"},{"file":"sounds/roulette/rouletteplay.mp3","hash":"QmRzTACYh9qyvpJFHTM6NwdsyrqA1ADbZ1MGWu2BjeANBJ"},{"file":"sounds/roulette/stacking.mp3","hash":"QmX8oubMYtyY5DyaGmrJZQdh4ZJKDs5F2YdcdbFmnUrvhj"},{"file":"sounds/roulette/win.mp3","hash":"QmQTFNkDzfB51r5kSUHzT1c9JSUfnzVo9hvzWAm4qCZHxC"},{"file":"sounds/slots/buttonBeep1.mp3","hash":"QmW1QVdwuAhdH1sSBs6FXybyqD5PFQrdwY2mdCms79p4qh"},{"file":"sounds/slots/jackpot1.mp3","hash":"QmSi8Gnj55gcWB5K59Cf5bga7mXTqbujMgtTqSap2UbzkT"},{"file":"sounds/slots/spinning2.mp3","hash":"QmbQSpxRc2H1y7AEJh8hW15DUxFnhDnD8wvBST6hyVxrad"},{"file":"sounds/slots/wheelLock.mp3","hash":"QmSBPSP66pm1LeW1VdweLtbv2amZEuxvKkkRrJKPWptojL"},{"file":"sounds/wasa-wasa-wasa.mp3","hash":"QmPUeT6FYRQ85aS4ChaSQnWaSX47DUAcnCuWmXhkG8nKDo"},{"file":"sounds/wilhem-scream.mp3","hash":"QmaoTeSEVq1kmzzUyryjBnNSjcw43jDwGNpS8sCaj47Ue2"}],"metadata":{"display":{"title":"Vegas Plaza","favicon":"favicon_asset"},"contact":{"name":"Decentraland","email":""},"owner":"","scene":{"parcels":["-71,52","-71,53","-71,54","-71,55","-71,56","-71,57","-71,58","-71,59","-71,60","-71,61","-71,62","-71,63","-71,64","-71,65","-71,66","-71,67","-71,68","-71,69","-71,70","-71,71","-70,52","-70,53","-70,54","-70,55","-70,56","-70,57","-70,58","-70,59","-70,60","-70,61","-70,62","-70,63","-70,64","-70,65","-70,66","-70,67","-70,68","-70,69","-70,70","-70,71","-69,52","-69,53","-69,54","-69,55","-69,56","-69,57","-69,58","-69,59","-69,60","-69,61","-69,62","-69,63","-69,64","-69,65","-69,66","-69,67","-69,68","-69,69","-69,70","-69,71","-68,52","-68,53","-68,54","-68,55","-68,56","-68,57","-68,58","-68,59","-68,60","-68,61","-68,62","-68,63","-68,64","-68,65","-68,66","-68,67","-68,68","-68,69","-68,70","-68,71","-67,52","-67,53","-67,54","-67,55","-67,56","-67,57","-67,58","-67,59","-67,60","-67,61","-67,62","-67,63","-67,64","-67,65","-67,66","-67,67","-67,68","-67,69","-67,70","-67,71","-66,52","-66,53","-66,54","-66,55","-66,56","-66,57","-66,58","-66,59","-66,60","-66,61","-66,62","-66,63","-66,64","-66,65","-66,66","-66,67","-66,68","-66,69","-66,70","-66,71","-65,52","-65,53","-65,54","-65,55","-65,56","-65,57","-65,58","-65,59","-65,60","-65,61","-65,62","-65,63","-65,64","-65,65","-65,66","-65,67","-65,68","-65,69","-65,70","-65,71","-64,52","-64,53","-64,54","-64,55","-64,56","-64,57","-64,58","-64,59","-64,60","-64,61","-64,62","-64,63","-64,64","-64,65","-64,66","-64,67","-64,68","-64,69","-64,70","-64,71","-63,52","-63,53","-63,54","-63,55","-63,56","-63,57","-63,58","-63,59","-63,60","-63,61","-63,62","-63,63","-63,64","-63,65","-63,66","-63,67","-63,68","-63,69","-63,70","-63,71","-62,52","-62,53","-62,54","-62,55","-62,56","-62,57","-62,58","-62,59","-62,60","-62,61","-62,62","-62,63","-62,64","-62,65","-62,66","-62,67","-62,68","-62,69","-62,70","-62,71","-61,52","-61,53","-61,54","-61,55","-61,56","-61,57","-61,58","-61,59","-61,60","-61,61","-61,62","-61,63","-61,64","-61,65","-61,66","-61,67","-61,68","-61,69","-61,70","-61,71","-60,52","-60,53","-60,54","-60,55","-60,56","-60,57","-60,58","-60,59","-60,60","-60,61","-60,62","-60,63","-60,64","-60,65","-60,66","-60,67","-60,68","-60,69","-60,70","-60,71","-59,52","-59,53","-59,54","-59,55","-59,56","-59,57","-59,58","-59,59","-59,60","-59,61","-59,62","-59,63","-59,64","-59,65","-59,66","-59,67","-59,68","-59,69","-59,70","-59,71","-58,52","-58,53","-58,54","-58,55","-58,56","-58,57","-58,58","-58,59","-58,60","-58,61","-58,62","-58,63","-58,64","-58,65","-58,66","-58,67","-58,68","-58,69","-58,70","-58,71","-57,52","-57,53","-57,54","-57,55","-57,56","-57,57","-57,58","-57,59","-57,60","-57,61","-57,62","-57,63","-57,64","-57,65","-57,66","-57,67","-57,68","-57,69","-57,70","-57,71","-56,52","-56,53","-56,54","-56,55","-56,56","-56,57","-56,58","-56,59","-56,60","-56,61","-56,62","-56,63","-56,64","-56,65","-56,66","-56,67","-56,68","-56,69","-56,70","-56,71","-55,52","-55,53","-55,54","-55,55","-55,56","-55,57","-55,58","-55,59","-55,60","-55,61","-55,62","-55,63","-55,64","-55,65","-55,66","-55,67","-55,68","-55,69","-55,70","-55,71","-54,52","-54,53","-54,54","-54,55","-54,56","-54,57","-54,58","-54,59","-54,60","-54,61","-54,62","-54,63","-54,64","-54,65","-54,66","-54,67","-54,68","-54,69","-54,70","-54,71","-53,52","-53,53","-53,54","-53,55","-53,56","-53,57","-53,58","-53,59","-53,60","-53,61","-53,62","-53,63","-53,64","-53,65","-53,66","-53,67","-53,68","-53,69","-53,70","-53,71","-52,52","-52,53","-52,54","-52,55","-52,56","-52,57","-52,58","-52,59","-52,60","-52,61","-52,62","-52,63","-52,64","-52,65","-52,66","-52,67","-52,68","-52,69","-52,70","-52,71"],"base":"-71,52"},"communications":{"type":"webrtc","signalling":"https://signalling-01.decentraland.org"},"policy":{"contentRating":"E","fly":true,"voiceEnabled":true,"blacklist":[],"teleportPosition":""},"main":"bin/game.js","tags":[],"spawnPoints":[{"name":"mainEntrance","position":{"x":54,"y":1.1,"z":108}},{"name":"brigeEntrance","position":{"x":138,"y":12,"z":108},"cameraTarget":{"x":150,"y":16.7,"z":108}},{"name":"townFair","position":{"x":156,"y":8,"z":209},"cameraTarget":{"x":158,"y":8,"z":207}},{"name":"castleRoom","position":{"x":192,"y":35,"z":108},"cameraTarget":{"x":190,"y":35,"z":108}},{"name":"trainingCamp","position":{"x":217,"y":1.1,"z":254}}]}}